Metadata-Version: 2.1
Name: pandoc-docx-helper
Version: 0.0.1
Summary: Pandoc filter for docx output to insert pagebreak at will
Author: Mico Papp based on Kazuki Yamamotos work
Keywords: pandoc filter docx
Classifier: Development Status :: 3 - Alpha
Classifier: Intended Audience :: Developers
Classifier: Topic :: Software Development :: Build Tools
Classifier: License :: OSI Approved :: MIT License
Classifier: Programming Language :: Python :: 3
Classifier: Programming Language :: Python :: 3.4
Classifier: Programming Language :: Python :: 3.5
Classifier: Programming Language :: Python :: 3.6
License-File: LICENSE
